pyslim/__init__.py
pyslim/_version.py
pyslim/methods.py
pyslim/mutate.py
pyslim/provenance.py
pyslim/slim_metadata.py
pyslim/slim_tables.py
pyslim/slim_tree_sequence.py
pyslim/spatial.py
pyslim/util.py
pyslim-1.1.0.dist-info/licenses/LICENSE
tests/__init__.py
tests/binary_derived_state.py
tests/recipe.slim
tests/test_annotate_msprime.py
tests/test_annotate_sexes.py
tests/test_annotation.py
tests/test_metadata.py
tests/test_mutate.py
tests/test_provenance.py
tests/test_read_slim.py
tests/test_reading.py
tests/test_recaptiation.py
tests/test_tree_sequence.py
tests/test_writing.py
tests/examples/make_v3_tests.sh
tests/examples/recipe_WF.slim
tests/examples/recipe_WF.v3.0.trees
tests/examples/recipe_WF.v3.2.trees
tests/examples/recipe_nonWF.slim
tests/examples/recipe_nonWF.v3.0.trees
tests/examples/recipe_nonWF.v3.2.trees
tests/examples/recipe_nucleotides.slim
tests/examples/recipe_record_everyone.slim
tests/examples/restart_WF.slim
tests/examples/restart_msprime.slim
tests/examples/restart_nonWF.slim
tests/examples/restart_nucleotides.slim
pyslim-1.1.0.dist-info/METADATA
pyslim-1.1.0.dist-info/WHEEL
pyslim-1.1.0.dist-info/top_level.txt
pyslim-1.1.0.dist-info/RECORD
