Metadata-Version: 2.4
Name: pyslim
Version: 1.1.0
Summary: Manipulate tree sequences produced by SLiM.
Home-page: https://github.com/tskit-dev/pyslim
Author: Peter Ralph
Author-email: petrel.harp@gmail.com
License: MIT
Project-URL: Bug Reports, https://github.com/tskit-dev/pyslim/issues
Project-URL: Source, https://github.com/tskit-dev/pyslim
Keywords: tree sequences,tskit
License-File: LICENSE
Requires-Dist: msprime>=1.0.1
Requires-Dist: tskit
Requires-Dist: numpy
Provides-Extra: dev
Dynamic: author
Dynamic: author-email
Dynamic: description
Dynamic: description-content-type
Dynamic: home-page
Dynamic: keywords
Dynamic: license
Dynamic: license-file
Dynamic: project-url
Dynamic: provides-extra
Dynamic: requires-dist
Dynamic: summary
